warrant_lite/__init__.py
warrant_lite/tests.py
warrant_lite-1.0.3.dist-info/METADATA
warrant_lite-1.0.3.dist-info/RECORD
warrant_lite-1.0.3.dist-info/WHEEL
warrant_lite-1.0.3.dist-info/top_level.txt
warrant_lite-1.0.3.dist-info/zip-safe
